flask_redis_stream_pubsub/__init__.py
flask_redis_stream_pubsub/consumer.py
flask_redis_stream_pubsub/producer.py
flask_redis_stream_pubsub/util.py
flask_redis_stream_pubsub-0.1.4.dist-info/LICENSE
flask_redis_stream_pubsub-0.1.4.dist-info/METADATA
flask_redis_stream_pubsub-0.1.4.dist-info/WHEEL
flask_redis_stream_pubsub-0.1.4.dist-info/RECORD
