Metadata-Version: 2.1
Name: flask-redis-stream-pubsub
Version: 0.1.4
Summary: flask-redis-stream-pubsub
Home-page: https://github.com/eininst/flask-redis-stream-pubsub
Author: 王梓清
Author-email: 9464553+superwzq1993@user.noreply.gitee.com
Requires-Python: >=3.8,<4.0
Classifier: Programming Language :: Python :: 3
Classifier: Programming Language :: Python :: 3.8
Classifier: Programming Language :: Python :: 3.9
Classifier: Programming Language :: Python :: 3.10
Classifier: Programming Language :: Python :: 3.11
Classifier: Programming Language :: Python :: 3.12
Classifier: Programming Language :: Python :: 3.13
Requires-Dist: croniter (==5.0.1)
Project-URL: Documentation, https://github.com/eininst/flask-redis-stream-pubsub
